policystack/__init__.py
policystack/__version__.py
policystack/cli.py
policystack/config.py
policystack/commands/__init__.py
policystack/commands/config.py
policystack/commands/info.py
policystack/commands/init.py
policystack/commands/install.py
policystack/commands/repo.py
policystack/commands/rollback.py
policystack/commands/search.py
policystack/commands/sync.py
policystack/commands/upgrade.py
policystack/commands/validate.py
policystack/core/__init__.py
policystack/core/backup_manager.py
policystack/core/change_detector.py
policystack/core/conflict_resolver.py
policystack/core/file_merger.py
policystack/core/git_repository.py
policystack/core/installer.py
policystack/core/marketplace.py
policystack/core/merger.py
policystack/core/registry.py
policystack/core/sync_manager.py
policystack/core/yaml_merger.py
policystack/models/__init__.py
policystack/models/backup.py
policystack/models/config.py
policystack/models/repository.py
policystack/models/template.py
policystack/utils/__init__.py
policystack/utils/console.py
policystack/utils/file_utils.py
policystack_cli-0.4.0.dist-info/licenses/LICENSE
policystack_cli-0.4.0.dist-info/METADATA
policystack_cli-0.4.0.dist-info/WHEEL
policystack_cli-0.4.0.dist-info/entry_points.txt
policystack_cli-0.4.0.dist-info/top_level.txt
policystack_cli-0.4.0.dist-info/RECORD
