Metadata-Version: 2.4
Name: policystack-cli
Version: 0.4.0
Summary: CLI tool for PolicyStack marketplace - discover, search and install configuration templates
Author-email: Asa Moore <asmoore@redhat.com>
Maintainer-email: Asa Moore <asmoore@redhat.com>
License: Apache-2.0
Project-URL: Homepage, https://github.com/PolicyStack/cli
Project-URL: Documentation, https://github.com/PolicyStack/cli
Project-URL: Repository, https://github.com/PolicyStack/cli
Project-URL: Issues, https://github.com/PolicyStack/cli/issues
Keywords: policystack,openshift,acm,gitops,kubernetes
Classifier: Development Status :: 4 - Beta
Classifier: Environment :: Console
Classifier: Intended Audience :: Developers
Classifier: Intended Audience :: System Administrators
Classifier: License :: OSI Approved :: Apache Software License
Classifier: Operating System :: OS Independent
Classifier: Programming Language :: Python
Classifier: Programming Language :: Python :: 3
Classifier: Programming Language :: Python :: 3.8
Classifier: Programming Language :: Python :: 3.9
Classifier: Programming Language :: Python :: 3.10
Classifier: Programming Language :: Python :: 3.11
Classifier: Programming Language :: Python :: 3.12
Classifier: Programming Language :: Python :: 3.13
Classifier: Topic :: Software Development :: Libraries :: Python Modules
Classifier: Topic :: System :: Systems Administration
Requires-Python: >=3.8
License-File: LICENSE
Requires-Dist: click>=8.1.0
Requires-Dist: rich>=13.0.0
Requires-Dist: pyyaml>=6.0
Requires-Dist: httpx>=0.24.0
Requires-Dist: pydantic>=2.0.0
Requires-Dist: tabulate>=0.9.0
Requires-Dist: packaging>=23.0
Requires-Dist: GitPython>=3.1.0
Requires-Dist: ruamel.yaml>=0.17.0
Requires-Dist: deepdiff
Requires-Dist: merge3>=0.0.13
Provides-Extra: dev
Requires-Dist: pytest>=7.0.0; extra == "dev"
Requires-Dist: pytest-cov>=4.0.0; extra == "dev"
Requires-Dist: pytest-asyncio>=0.21.0; extra == "dev"
Requires-Dist: black>=23.0.0; extra == "dev"
Requires-Dist: isort>=5.12.0; extra == "dev"
Requires-Dist: flake8>=6.0.0; extra == "dev"
Requires-Dist: mypy>=1.0.0; extra == "dev"
Requires-Dist: tox>=4.0.0; extra == "dev"
Requires-Dist: pre-commit>=3.0.0; extra == "dev"
Requires-Dist: types-PyYAML; extra == "dev"
Requires-Dist: types-tabulate; extra == "dev"
Dynamic: license-file
